jsonschema_validator/__init__.py
jsonschema_validator/json_schema.py
jsonschema_validator/py.typed
jsonschema_validator_new-0.3.2.dist-info/LICENSE
jsonschema_validator_new-0.3.2.dist-info/METADATA
jsonschema_validator_new-0.3.2.dist-info/WHEEL
jsonschema_validator_new-0.3.2.dist-info/entry_points.txt
jsonschema_validator_new-0.3.2.dist-info/RECORD
