Metadata-Version: 2.1
Name: jsonschema-validator-new
Version: 0.3.2
Summary: Tool to validate files against a JSON Schema
Home-page: https://github.com/sbrunner/jsonschema-validator
License: BSD-2-Clause
Keywords: jsonschema,types
Author: Stéphane Brunner
Author-email: stephane.brunner@gmail.com
Requires-Python: >=3.9
Classifier: Development Status :: 4 - Beta
Classifier: Environment :: Console
Classifier: Intended Audience :: Developers
Classifier: License :: OSI Approved :: BSD License
Classifier: Operating System :: OS Independent
Classifier: Programming Language :: Python
Classifier: Programming Language :: Python :: 3
Classifier: Programming Language :: Python :: 3.9
Classifier: Programming Language :: Python :: 3.10
Classifier: Programming Language :: Python :: 3.11
Classifier: Programming Language :: Python :: 3.12
Classifier: Topic :: Software Development :: Code Generators
Classifier: Typing :: Typed
Requires-Dist: jsonschema
Requires-Dist: requests
Requires-Dist: ruamel.yaml
Project-URL: Repository, https://github.com/sbrunner/jsonschema-validator
